alquimodelia/__init__.py
alquimodelia/__version__.py
alquimodelia/alquimodelia.py
alquimodelia/builders/__init__.py
alquimodelia/builders/base_builder.py
alquimodelia/builders/cnn.py
alquimodelia/builders/fcnn.py
alquimodelia/builders/lstm.py
alquimodelia/builders/notes.md
alquimodelia/builders/resnet.py
alquimodelia/builders/transformer copy.py
alquimodelia/builders/transformer.py
alquimodelia/builders/tryouts.py
alquimodelia/builders/unet.py
alquimodelia/utils.py
alquimodelia-0.0.7.dist-info/METADATA
alquimodelia-0.0.7.dist-info/WHEEL
alquimodelia-0.0.7.dist-info/licenses/LICENSE
alquimodelia-0.0.7.dist-info/RECORD
