Metadata-Version: 2.4
Name: alquimodelia
Version: 0.0.7
Summary: Keras based model builder
License: LICENSE
License-File: LICENSE
Keywords: python,machine learning,forecast,model builder
Author: João Santos
Author-email: jotaflame@gmail.com
Requires-Python: >=3.9,<4.0
Classifier: License :: Other/Proprietary License
Classifier: Programming Language :: Python :: 3
Classifier: Programming Language :: Python :: 3.9
Classifier: Programming Language :: Python :: 3.10
Classifier: Programming Language :: Python :: 3.11
Classifier: Programming Language :: Python :: 3.12
Classifier: Programming Language :: Python :: 3.13
Classifier: Programming Language :: Python :: 3.14
Provides-Extra: jax
Provides-Extra: tensorflow
Provides-Extra: torch
Requires-Dist: jax ; extra == "jax"
Requires-Dist: keras (>=3)
Requires-Dist: numpy
Requires-Dist: pandas
Requires-Dist: pytorch ; extra == "torch"
Requires-Dist: tensorflow ; extra == "tensorflow"
Project-URL: Bug Tracker, https://github.com/alquimodelia/alquimodelia/issues
Project-URL: Documentation, https://alquimodelia.github.io/alquimodelia/
Project-URL: Homepage, https://github.com/alquimodelia/alquimodelia
Project-URL: Repository, https://github.com/alquimodelia/alquimodelia
Project-URL: Source Code, https://github.com/alquimodelia/alquimodelia
